AUTHORS
LICENSE
MANIFEST.in
README.rst
requirements_dev.py26.txt
requirements_dev.txt
setup.py
docs/Makefile
docs/conf.py
docs/index.rst
docs/make.bat
docs/releases.rst
docs/internals/contributing.rst
docs/internals/roadmap.rst
duvet/__init__.py
duvet/__main__.py
duvet/view.py
duvet/widgets.py
duvet.egg-info/PKG-INFO
duvet.egg-info/SOURCES.txt
duvet.egg-info/dependency_links.txt
duvet.egg-info/entry_points.txt
duvet.egg-info/requires.txt
duvet.egg-info/top_level.txt
tests/__init__.py