Metadata-Version: 1.1
Name: duvet
Version: 0.1.2
Summary: A GUI tool for visualizing code coverage results.
Home-page: http://pybee.org/duvet
Author: Russell Keith-Magee
Author-email: russell@keith-magee.com
License: New BSD
Platform: UNKNOWN
Classifier: Development Status :: 4 - Beta
Classifier: Intended Audience :: Developers
Classifier: License :: OSI Approved :: BSD License
Classifier: Operating System :: OS Independent
Classifier: Programming Language :: Python :: 2
Classifier: Topic :: Software Development
Classifier: Topic :: Utilities
